pointwise/__init__.py
pointwise/core/__init__.py
pointwise/tests/__init__.py
pointwise/tests/test_1984.py
pointwise-0.1.0.dev2.dist-info/licenses/LICENSE.txt
pointwise-0.1.0.dev2.dist-info/METADATA
pointwise-0.1.0.dev2.dist-info/WHEEL
pointwise-0.1.0.dev2.dist-info/top_level.txt
pointwise-0.1.0.dev2.dist-info/RECORD
