Metadata-Version: 2.4
Name: pointwise
Version: 0.1.0.dev2
Summary: pointwise
Author-email: Johannes <johannes.programming@gmail.com>
License: The MIT License (MIT)
Project-URL: Download, https://pypi.org/project/pointwise/#files
Project-URL: Index, https://pypi.org/project/pointwise/
Project-URL: Source, https://github.com/johannes-programming/pointwise/
Project-URL: Website, https://pointwise.johannes-programming.online/
Classifier: Development Status :: 3 - Alpha
Classifier: License :: OSI Approved :: MIT License
Classifier: Natural Language :: English
Classifier: Operating System :: OS Independent
Classifier: Programming Language :: Python
Classifier: Programming Language :: Python :: 3
Classifier: Programming Language :: Python :: 3 :: Only
Classifier: Typing :: Typed
Requires-Python: >=3.11
License-File: LICENSE.txt
Dynamic: license-file
